sheetsu/__init__.py
sheetsu/client.py
sheetsu/exceptions.py
sheetsu/core/__init__.py
sheetsu/core/core.py
sheetsu/core/create.py
sheetsu/core/delete.py
sheetsu/core/read.py
sheetsu/core/search.py
sheetsu/core/update.py
sheetsu/tests/__init__.py
sheetsu/tests/test_create.py
sheetsu/tests/test_delete.py
sheetsu/tests/test_read.py
sheetsu/tests/test_search.py
sheetsu/tests/test_update.py
sheetsu-1.1.0.dist-info/DESCRIPTION.rst
sheetsu-1.1.0.dist-info/METADATA
sheetsu-1.1.0.dist-info/RECORD
sheetsu-1.1.0.dist-info/WHEEL
sheetsu-1.1.0.dist-info/metadata.json
sheetsu-1.1.0.dist-info/top_level.txt
